briefcasebrain_sdk/__init__.py
briefcasebrain_sdk/api_client.py
briefcasebrain_sdk/api_response.py
briefcasebrain_sdk/configuration.py
briefcasebrain_sdk/exceptions.py
briefcasebrain_sdk/py.typed
briefcasebrain_sdk/rest.py
briefcasebrain_sdk/api/__init__.py
briefcasebrain_sdk/api/contracts_api.py
briefcasebrain_sdk/api/legal_research_api.py
briefcasebrain_sdk/api/queries_api.py
briefcasebrain_sdk/api/query_enhancement_api.py
briefcasebrain_sdk/api/user_api.py
briefcasebrain_sdk/api/workflows_api.py
briefcasebrain_sdk/models/__init__.py
briefcasebrain_sdk/models/api_contracts_templates_post201_response.py
briefcasebrain_sdk/models/api_contracts_templates_post_request.py
briefcasebrain_sdk/models/api_queries_get200_response.py
briefcasebrain_sdk/models/api_queries_get200_response_pagination.py
briefcasebrain_sdk/models/api_queries_get200_response_queries_inner.py
briefcasebrain_sdk/models/api_queries_post201_response.py
briefcasebrain_sdk/models/api_queries_post_request.py
briefcasebrain_sdk/models/api_user_credits_get200_response.py
briefcasebrain_sdk/models/api_workflows_get200_response.py
briefcasebrain_sdk/models/api_workflows_post201_response.py
briefcasebrain_sdk/models/api_workflows_post_request.py
briefcasebrain_sdk/models/api_workflows_post_request_steps_inner.py
briefcasebrain_sdk/models/contract_template.py
briefcasebrain_sdk/models/enhance_query_request.py
briefcasebrain_sdk/models/enhance_query_response.py
briefcasebrain_sdk/models/enhance_query_response_enhanced_queries_inner.py
briefcasebrain_sdk/models/error.py
briefcasebrain_sdk/models/legal_research_request.py
briefcasebrain_sdk/models/legal_research_request_conversation_history_inner.py
briefcasebrain_sdk/models/legal_research_response.py
briefcasebrain_sdk/models/legal_research_response_relevant_cases_inner.py
briefcasebrain_sdk/models/legal_research_response_relevant_statutes_inner.py
briefcasebrain_sdk/models/success.py
briefcasebrain_sdk/models/user.py
briefcasebrain_sdk/models/workflow.py
briefcasebrain_sdk-1.0.0.dist-info/METADATA
briefcasebrain_sdk-1.0.0.dist-info/WHEEL
briefcasebrain_sdk-1.0.0.dist-info/top_level.txt
briefcasebrain_sdk-1.0.0.dist-info/RECORD
