Metadata-Version: 2.4
Name: briefcasebrain-sdk
Version: 1.0.0
Summary: Official Python SDK for BriefcaseBrain Legal AI Platform
Home-page: https://github.com/briefcasebrain/sdk
Author: BriefcaseBrain Support
Author-email: BriefcaseBrain Support <support@briefcasebrain.io>
License: MIT
Project-URL: Repository, https://github.com/briefcasebrain/sdk
Project-URL: Homepage, https://briefcasebrain.io
Project-URL: Documentation, https://docs.briefcasebrain.io
Project-URL: Bug Reports, https://github.com/briefcasebrain/sdk/issues
Project-URL: Changelog, https://github.com/briefcasebrain/sdk/blob/main/packages/python-sdk/CHANGELOG.md
Keywords: legal,ai,legal-research,contracts,briefcasebrain,sdk,api
Classifier: Development Status :: 5 - Production/Stable
Classifier: Intended Audience :: Developers
Classifier: License :: OSI Approved :: MIT License
Classifier: Programming Language :: Python :: 3
Classifier: Programming Language :: Python :: 3.9
Classifier: Programming Language :: Python :: 3.10
Classifier: Programming Language :: Python :: 3.11
Classifier: Programming Language :: Python :: 3.12
Classifier: Topic :: Software Development :: Libraries :: Python Modules
Classifier: Topic :: Internet :: WWW/HTTP :: Dynamic Content
Classifier: Topic :: Scientific/Engineering :: Artificial Intelligence
Requires-Python: >= 3.9
Requires-Dist: urllib3<3.0.0,>=2.1.0
Requires-Dist: python-dateutil>=2.8.2
Requires-Dist: pydantic>=2
Requires-Dist: typing-extensions>=4.7.1
Dynamic: author
Dynamic: home-page
Dynamic: requires-python
